csae_pyutils/__init__.py
csae_pyutils-0.2.dist-info/licenses/LICENSE
csae_pyutils-0.2.dist-info/METADATA
csae_pyutils-0.2.dist-info/WHEEL
csae_pyutils-0.2.dist-info/top_level.txt
csae_pyutils-0.2.dist-info/RECORD
