Metadata-Version: 2.4
Name: csae-pyutils
Version: 0.2
Summary: some python function used in several places
Author-email: Peter Andorfer <p.andorfer@gmail.com>
License: MIT License
Requires-Python: >=3.9
License-File: LICENSE
Requires-Dist: pandas
Requires-Dist: pyocclient
Requires-Dist: requests
Dynamic: license-file
